fuma/CLI.py
fuma/CompareFusionsBySpanningGenes.py
fuma/ComparisonTriangle.py
fuma/Fusion.py
fuma/FusionDetectionExperiment.py
fuma/Gene.py
fuma/GeneAnnotation.py
fuma/MergedFusion.py
fuma/OverlapComplex.py
fuma/ParseBED.py
fuma/Readers.py
fuma/__init__.py
fuma-4.0.0.data/scripts/chimerascan-exclude-transcriptome-events
fuma-4.0.0.data/scripts/chimerascan-relative-bedpe-to-CG
fuma-4.0.0.data/scripts/defuse-clusters-to-CG
fuma-4.0.0.data/scripts/fuma
fuma-4.0.0.data/scripts/fuma-gencode-gtf-to-bed
fuma-4.0.0.data/scripts/fuma-list-to-boolean-list
fuma-4.0.0.data/scripts/fusioncatcher-to-CG
fuma-4.0.0.dist-info/COPYING
fuma-4.0.0.dist-info/LICENSE
fuma-4.0.0.dist-info/METADATA
fuma-4.0.0.dist-info/WHEEL
fuma-4.0.0.dist-info/top_level.txt
fuma-4.0.0.dist-info/RECORD
