Metadata-Version: 2.1
Name: fuma
Version: 4.0.0
Summary: Fusion Matcher
Home-page: https://github.com/yhoogstrate/fuma
Author: Youri Hoogstrate
Maintainer: Youri Hoogstrate
License: GNU General Public License v3 (GPLv3)
Platform: any
Classifier: Environment :: Console
Classifier: Intended Audience :: Science/Research
Classifier: License :: OSI Approved :: GNU General Public License v3 (GPLv3)
Classifier: Operating System :: OS Independent
Classifier: Topic :: Scientific/Engineering
Classifier: Topic :: Scientific/Engineering :: Bio-Informatics
License-File: LICENSE
License-File: COPYING
Requires-Dist: numpy
Requires-Dist: HTSeq (>=0.6.1)
Requires-Dist: nose
